nanolocal/__init__.py
nanolocal/nl_module.py
nanolocal/common/__init__.py
nanolocal/common/nl_block_tools.py
nanolocal/common/nl_initialise.py
nanolocal/common/nl_nanolib.py
nanolocal/common/nl_parse_config.py
nanolocal/common/nl_rpc.py
nanolocal/testcases/__init__.py
nanolocal/testcases/basic.py
nano_local-0.1.5.dist-info/METADATA
nano_local-0.1.5.dist-info/WHEEL
nano_local-0.1.5.dist-info/top_level.txt
nano_local-0.1.5.dist-info/RECORD
